rx_selection/cache_data.py
rx_selection/cutflow.py
rx_selection/differential_efficiency.py
rx_selection/ds_getter.py
rx_selection/efficiency.py
rx_selection/ndict.py
rx_selection/selection.py
rx_selection/tests.py
rx_selection/truth_matching.py
rx_selection/utilities.py
rx_selection/version_management.py
rx_selection-0.1.8.data/scripts/job_sel_ihep
rx_selection-0.1.8.data/scripts/submit_selection
rx_selection_data/selection/v1.yaml
rx_selection_data/validation/v1.yaml
rx_selection_scripts/apply_selection.py
rx_selection_scripts/job_sel_ihep
rx_selection_scripts/make_jobs_list.py
rx_selection_scripts/submit_selection
rx_selection_scripts/validate_sample.py
rx_selection-0.1.8.dist-info/METADATA
rx_selection-0.1.8.dist-info/WHEEL
rx_selection-0.1.8.dist-info/entry_points.txt
rx_selection-0.1.8.dist-info/top_level.txt
rx_selection-0.1.8.dist-info/RECORD
