Metadata-Version: 2.2
Name: rx_selection
Version: 0.1.8
Summary: Project used to apply selection to ntuples used for RX measurements filtered and skimmed by post_ap project
Requires-Dist: data-manipulation-utilities
Requires-Dist: rx_data
Requires-Dist: numexpr
Requires-Dist: numpy
Requires-Dist: jacobi
Requires-Dist: joblib
Requires-Dist: pandas
Requires-Dist: numpy>=2.2.2
Requires-Dist: matplotlib
Requires-Dist: ap_utilities
Provides-Extra: dev
Requires-Dist: pytest; extra == "dev"
